sz_mcp_server/__init__.py
sz_mcp_server/log.py
sz_mcp_server/sz_server.py
sz_mcp_server/server/__init__.py
sz_mcp_server/server/local_tools.py
sz_mcp_server/server/utils.py
ai_indeed_mcp_server-1.0.0.dist-info/METADATA
ai_indeed_mcp_server-1.0.0.dist-info/WHEEL
ai_indeed_mcp_server-1.0.0.dist-info/entry_points.txt
ai_indeed_mcp_server-1.0.0.dist-info/licenses/LICENSE
ai_indeed_mcp_server-1.0.0.dist-info/RECORD
