Metadata-Version: 2.4
Name: Ai_Indeed_mcp_server
Version: 1.0.0
Summary: Query and execute robotic processes through standardized tool calls.
Author-email: Ai-Indeed <contact@i-i.ai>
License: MIT
License-File: LICENSE
Keywords: mcp,robot,sz_mcp_server,z-bot
Classifier: License :: OSI Approved :: MIT License
Classifier: Operating System :: Microsoft :: Windows
Classifier: Programming Language :: Python :: 3
Classifier: Programming Language :: Python :: 3 :: Only
Requires-Python: >=3.12
Requires-Dist: mcp[cli]>=1.24.0
